geoshaha_haoyu/__init__.py
geoshaha_haoyu/common.py
geoshaha_haoyu/geoshaha_haoyu.py
geoshaha_haoyu-0.0.2.dist-info/LICENSE
geoshaha_haoyu-0.0.2.dist-info/METADATA
geoshaha_haoyu-0.0.2.dist-info/WHEEL
geoshaha_haoyu-0.0.2.dist-info/top_level.txt
geoshaha_haoyu-0.0.2.dist-info/RECORD
